bosdyn/__init__.py
bosdyn/mission/__init__.py
bosdyn/mission/client.py
bosdyn/mission/constants.py
bosdyn/mission/exceptions.py
bosdyn/mission/remote_client.py
bosdyn/mission/server_util.py
bosdyn/mission/util.py
bosdyn_mission-5.0.1.dist-info/METADATA
bosdyn_mission-5.0.1.dist-info/WHEEL
bosdyn_mission-5.0.1.dist-info/top_level.txt
bosdyn_mission-5.0.1.dist-info/RECORD
